LICENSE
README.md
setup.py
py_ext_to_format/__init__.py
py_ext_to_format/formats.json
py_ext_to_format.egg-info/PKG-INFO
py_ext_to_format.egg-info/SOURCES.txt
py_ext_to_format.egg-info/dependency_links.txt
py_ext_to_format.egg-info/top_level.txt