Metadata-Version: 2.1
Name: py-ext-to-format
Version: 0.0.1
Summary: A simple tool to convert file extensions to file formats
Home-page: https://github.com/elonsalfati/py-ext-to-format
Author: Elon Salfati
Author-email: elon@salfati.io
License: UNKNOWN
Platform: UNKNOWN
License-File: LICENSE
